prediction/__init__.py
prediction/predictor.py
prediction/py.typed
alvan_text_predictor-1.1.1.dist-info/LICENSE
alvan_text_predictor-1.1.1.dist-info/METADATA
alvan_text_predictor-1.1.1.dist-info/WHEEL
alvan_text_predictor-1.1.1.dist-info/top_level.txt
alvan_text_predictor-1.1.1.dist-info/RECORD
