Metadata-Version: 2.1
Name: alvan-text-predictor
Version: 1.1.1
Summary: The text prediction module for ALVAN 5.
Author: Craig Sirota
Author-email: Craig Sirota <craigmsirota@gmail.com>
License: MIT License
Platform: unix
Platform: linux
Platform: osx
Platform: cygwin
Platform: win32
Requires-Python: >=3.12
License-File: LICENSE
Provides-Extra: testing
Requires-Dist: pytest >=6.0 ; extra == 'testing'
Requires-Dist: pytest-cov >=2.0 ; extra == 'testing'
Requires-Dist: mypy >=0.910 ; extra == 'testing'
Requires-Dist: flake8 >=3.9 ; extra == 'testing'
Requires-Dist: tox >=3.24 ; extra == 'testing'
